mazegenerator/__main__.py
mazegenerator/create_output_image.py
mazegenerator/g.py
mazegenerator/generate.py
mazegenerator/mazeutils.py
mazegenerator/strings.py
mazegenerator-1.2.1.dist-info/LICENSE
mazegenerator-1.2.1.dist-info/METADATA
mazegenerator-1.2.1.dist-info/WHEEL
mazegenerator-1.2.1.dist-info/entry_points.txt
mazegenerator-1.2.1.dist-info/top_level.txt
mazegenerator-1.2.1.dist-info/RECORD
